pssm_promoter_calculator.py
pssm_promoter_tool-1.0.6.dist-info/LICENSE.txt
pssm_promoter_tool-1.0.6.dist-info/METADATA
pssm_promoter_tool-1.0.6.dist-info/WHEEL
pssm_promoter_tool-1.0.6.dist-info/top_level.txt
pssm_promoter_tool-1.0.6.dist-info/RECORD
