Metadata-Version: 2.1
Name: pssm-promoter-tool
Version: 1.0.6
Summary: The tool applies direct and inverted Codon Restrained Promoter Silencing method to the provided gene sequence
Home-page: https://github.com/ellinium/PSSM_PromoterTool
Author: Ellina Trofimova
Author-email: ellina.trofimova@gmail.com
License: GNU General Public License
Keywords: promoter prediction transcription rate
License-File: LICENSE.txt
Requires-Dist: biopython
Requires-Dist: click
Requires-Dist: cloudpickle
Requires-Dist: dask
Requires-Dist: distributed
Requires-Dist: fsspec
Requires-Dist: importlib-metadata
Requires-Dist: joblib
Requires-Dist: locket
Requires-Dist: msgpack
Requires-Dist: numpy
Requires-Dist: packaging
Requires-Dist: pandas
Requires-Dist: partd
Requires-Dist: psutil
Requires-Dist: python-dateutil
Requires-Dist: pytz
Requires-Dist: scikit-learn
Requires-Dist: scipy
Requires-Dist: six
Requires-Dist: sortedcontainers
Requires-Dist: tblib
Requires-Dist: threadpoolctl
Requires-Dist: toolz
Requires-Dist: tornado
Requires-Dist: urllib3
Requires-Dist: zict
Requires-Dist: zipp
